huaweicloudsdkdgc/__init__.py
huaweicloudsdkdgc/v1/__init__.py
huaweicloudsdkdgc/v1/dgc_async_client.py
huaweicloudsdkdgc/v1/dgc_client.py
huaweicloudsdkdgc/v1/model/__init__.py
huaweicloudsdkdgc/v1/model/basic_config.py
huaweicloudsdkdgc/v1/model/cancel_script_request.py
huaweicloudsdkdgc/v1/model/cancel_script_response.py
huaweicloudsdkdgc/v1/model/condition.py
huaweicloudsdkdgc/v1/model/create_job_request.py
huaweicloudsdkdgc/v1/model/create_job_response.py
huaweicloudsdkdgc/v1/model/create_resource_request.py
huaweicloudsdkdgc/v1/model/create_resource_response.py
huaweicloudsdkdgc/v1/model/create_script_request.py
huaweicloudsdkdgc/v1/model/create_script_response.py
huaweicloudsdkdgc/v1/model/cron.py
huaweicloudsdkdgc/v1/model/cron_trigger.py
huaweicloudsdkdgc/v1/model/delete_job_request.py
huaweicloudsdkdgc/v1/model/delete_job_response.py
huaweicloudsdkdgc/v1/model/delete_req.py
huaweicloudsdkdgc/v1/model/delete_resource_request.py
huaweicloudsdkdgc/v1/model/delete_resource_response.py
huaweicloudsdkdgc/v1/model/delete_script_request.py
huaweicloudsdkdgc/v1/model/delete_script_response.py
huaweicloudsdkdgc/v1/model/depend_job.py
huaweicloudsdkdgc/v1/model/depend_package.py
huaweicloudsdkdgc/v1/model/depend_work_space_job.py
huaweicloudsdkdgc/v1/model/event.py
huaweicloudsdkdgc/v1/model/execute_script_req.py
huaweicloudsdkdgc/v1/model/execute_script_request.py
huaweicloudsdkdgc/v1/model/execute_script_response.py
huaweicloudsdkdgc/v1/model/export_job_list_request.py
huaweicloudsdkdgc/v1/model/export_job_list_response.py
huaweicloudsdkdgc/v1/model/export_job_req.py
huaweicloudsdkdgc/v1/model/export_job_request.py
huaweicloudsdkdgc/v1/model/export_job_response.py
huaweicloudsdkdgc/v1/model/export_jobs_req.py
huaweicloudsdkdgc/v1/model/file_path.py
huaweicloudsdkdgc/v1/model/import_file_req.py
huaweicloudsdkdgc/v1/model/import_job_request.py
huaweicloudsdkdgc/v1/model/import_job_response.py
huaweicloudsdkdgc/v1/model/job.py
huaweicloudsdkdgc/v1/model/job_alarm.py
huaweicloudsdkdgc-3.1.184.dist-info/METADATA
huaweicloudsdkdgc-3.1.184.dist-info/WHEEL
huaweicloudsdkdgc-3.1.184.dist-info/licenses/LICENSE
huaweicloudsdkdgc-3.1.184.dist-info/RECORD
